setup.cfg
setup.py
docs/HISTORY.txt
docs/INSTALL.txt
docs/LICENSE.GPL
docs/LICENSE.txt
sc/__init__.py
sc.kupu.objectsupport.egg-info/PKG-INFO
sc.kupu.objectsupport.egg-info/SOURCES.txt
sc.kupu.objectsupport.egg-info/dependency_links.txt
sc.kupu.objectsupport.egg-info/entry_points.txt
sc.kupu.objectsupport.egg-info/namespace_packages.txt
sc.kupu.objectsupport.egg-info/not-zip-safe
sc.kupu.objectsupport.egg-info/requires.txt
sc.kupu.objectsupport.egg-info/top_level.txt
sc/kupu/__init__.py
sc/kupu/objectsupport/README.txt
sc/kupu/objectsupport/__init__.py
sc/kupu/objectsupport/configure.zcml
sc/kupu/objectsupport/setuphandlers.py
sc/kupu/objectsupport/tests.py
sc/kupu/objectsupport/version.txt
sc/kupu/objectsupport/profiles/default/import_steps.xml
sc/kupu/objectsupport/profiles/default/kupu.xml
sc/kupu/objectsupport/profiles/default/metadata.xml
sc/kupu/objectsupport/profiles/default/sc.kupu.objectsupport.txt