Metadata-Version: 1.0
Name: sc.kupu.objectsupport
Version: 1.0
Summary: UNKNOWN
Home-page: http://svn.plone.org/svn/plone/plone.app.example
Author: Plone Foundation
Author-email: plone-developers@lists.sourceforge.net
License: GPL
Platform: UNKNOWN
Classifier: Framework :: Plone
Classifier: Programming Language :: Python
Classifier: Topic :: Software Development :: Libraries :: Python Modules
